friendly_exceptions/__init__.py
friendly_exceptions/cli.py
friendly_exceptions/config.py
friendly_exceptions/core.py
friendly_exceptions/logging.py
friendly_exceptions/handlers/__init__.py
friendly_exceptions/handlers/assertion_error.py
friendly_exceptions/handlers/attribute_error.py
friendly_exceptions/handlers/base.py
friendly_exceptions/handlers/connection_error.py
friendly_exceptions/handlers/file_not_found_error.py
friendly_exceptions/handlers/import_error.py
friendly_exceptions/handlers/indentation_error.py
friendly_exceptions/handlers/index_error.py
friendly_exceptions/handlers/is_a_directory_error.py
friendly_exceptions/handlers/json_decode_error.py
friendly_exceptions/handlers/key_error.py
friendly_exceptions/handlers/memory_error.py
friendly_exceptions/handlers/name_error.py
friendly_exceptions/handlers/not_implemented_error.py
friendly_exceptions/handlers/os_error.py
friendly_exceptions/handlers/overflow_error.py
friendly_exceptions/handlers/permission_error.py
friendly_exceptions/handlers/recursion_error.py
friendly_exceptions/handlers/runtime_error.py
friendly_exceptions/handlers/syntax_error.py
friendly_exceptions/handlers/system_error.py
friendly_exceptions/handlers/timeout_error.py
friendly_exceptions/handlers/type_error.py
friendly_exceptions/handlers/unicode_error.py
friendly_exceptions/handlers/value_error.py
friendly_exceptions/handlers/zero_division_error.py
friendly_exceptions-0.0.1.dist-info/licenses/LICENSE
friendly_exceptions-0.0.1.dist-info/METADATA
friendly_exceptions-0.0.1.dist-info/WHEEL
friendly_exceptions-0.0.1.dist-info/entry_points.txt
friendly_exceptions-0.0.1.dist-info/top_level.txt
friendly_exceptions-0.0.1.dist-info/RECORD
