Metadata-Version: 2.4
Name: friendly-exceptions
Version: 0.0.1
Summary: Human-readable exception explanations in Russian and English with smart suggestions
Home-page: https://github.com/artemjs/Pythonlibs/tree/friendly_exceptions/friendly_exceptions%200.0.1
Author: artemjs
Author-email: artemjs <artemjson@gmail.com>
License: MIT
Project-URL: Homepage, https://github.com/artemjs/Pythonlibs/tree/friendly_exceptions/friendly_exceptions%200.0.1
Project-URL: Documentation, https://github.com/artemjs/Pythonlibs/tree/friendly_exceptions/friendly_exceptions%200.0.1
Project-URL: Repository, https://github.com/artemjs/Pythonlibs.git
Project-URL: Bug Tracker, https://github.com/artemjs/Pythonlibs/issues
Keywords: exceptions,error-handling,debugging,human-readable,russian,english
Classifier: Development Status :: 5 - Production/Stable
Classifier: Intended Audience :: Developers
Classifier: License :: OSI Approved :: MIT License
Classifier: Operating System :: OS Independent
Classifier: Programming Language :: Python :: 3
Classifier: Programming Language :: Python :: 3.7
Classifier: Programming Language :: Python :: 3.8
Classifier: Programming Language :: Python :: 3.9
Classifier: Programming Language :: Python :: 3.10
Classifier: Programming Language :: Python :: 3.11
Classifier: Programming Language :: Python :: 3.12
Classifier: Topic :: Software Development :: Libraries :: Python Modules
Classifier: Topic :: Software Development :: Testing
Classifier: Topic :: Software Development :: Quality Assurance
Requires-Python: >=3.7
License-File: LICENSE
Provides-Extra: dev
Requires-Dist: pytest>=6.0; extra == "dev"
Requires-Dist: pytest-cov>=2.0; extra == "dev"
Requires-Dist: black>=21.0; extra == "dev"
Requires-Dist: flake8>=3.8; extra == "dev"
Requires-Dist: mypy>=0.800; extra == "dev"
Provides-Extra: docs
Requires-Dist: sphinx>=4.0; extra == "docs"
Requires-Dist: sphinx-rtd-theme>=1.0; extra == "docs"
Dynamic: author
Dynamic: home-page
Dynamic: license-file
Dynamic: requires-python
